<?xml version="1.0" encoding="utf-8"?>
<Application>
  <Views Id="Views">
    <DetailView Id="Incidente_DetailView">
      <Layout Id="Layout">
        <LayoutGroup Id="Main">
          <LayoutGroup Id="SimpleEditors">
            <LayoutGroup Id="Incidente">
              <LayoutGroup Id="Incidente_col1">
                <LayoutItem Id="Titulo" Index="7" RelativeSize="9.23076923076923" />
              </LayoutGroup>
            </LayoutGroup>
          </LayoutGroup>
        </LayoutGroup>
      </Layout>
    </DetailView>
  </Views>
</Application>